basefunctions/__init__.py
basefunctions/config_handler.py
basefunctions/database_handler.py
basefunctions/decorators.py
basefunctions/filefunctions.py
basefunctions/observer.py
basefunctions/secret_handler.py
basefunctions/threadpool.py
basefunctions/utils.py
basefunctions-0.4.3.6.dist-info/METADATA
basefunctions-0.4.3.6.dist-info/WHEEL
basefunctions-0.4.3.6.dist-info/top_level.txt
basefunctions-0.4.3.6.dist-info/RECORD
