Metadata-Version: 2.2
Name: basefunctions
Version: 0.4.3.6
Summary: simple library to have some commonly used functions for everyday purpose
Author-email: NeuralDevelopment <neutro2@outlook.de>
Project-URL: Homepage, https://dev.azure.com/neuraldevelopment/basefunctions
Classifier: Programming Language :: Python :: 3
Classifier: License :: OSI Approved :: MIT License
Classifier: Operating System :: OS Independent
Classifier: Programming Language :: Python :: 3.9
Classifier: Programming Language :: Python :: 3.10
Classifier: Programming Language :: Python :: 3.11
Classifier: Programming Language :: Python :: 3.12
Requires-Python: >=3.9
Requires-Dist: load_dotenv>=0.1.0
Requires-Dist: mysql-connector-python>=9.1.0
Requires-Dist: pandas>=2.0
Requires-Dist: psycopg2-binary>=2.9
Requires-Dist: pyyaml>=6.0
Requires-Dist: sqlalchemy>=2.0
Provides-Extra: dev
Provides-Extra: test
